{
    "configuration": "config/hydra/budget/sa_mean_10k_mpi.json",
    "FOR_SA_MIN_MEAN_BT_10k": {
        "repetitions": 19,
        "scenario": "/localsearch/scenarios/hydra/vanilla/foraging_bt.argos",
        "architecture": "BT",
        "initial_controller": "minimal",
        "result_directory": "/budget/foraging/budget_10k"
    },
    "FOR_SA_MIN_MEAN_FSM_10k": {
        "repetitions": 19,
        "scenario": "/localsearch/scenarios/hydra/vanilla/foraging.argos",
        "architecture": "FSM",
        "initial_controller": "minimal",
        "result_directory": "/budget/foraging/budget_10k"
    },
    "AAC_SA_MIN_MEAN_BT_10k": {
        "repetitions": 19,
        "scenario": "/localsearch/scenarios/hydra/vanilla/aac_bt.argos",
        "architecture": "BT",
        "initial_controller": "minimal",
        "result_directory": "/budget/aac/budget_10k"
    },
    "AAC_SA_MIN_MEAN_FSM_10k": {
        "repetitions": 19,
        "scenario": "/localsearch/scenarios/hydra/vanilla/aac_fsm.argos",
        "architecture": "FSM",
        "initial_controller": "minimal",
        "result_directory": "/budget/aac/budget_10k"
    }
}